pytest_pyq/__init__.py
pytest_pyq/conftest.py
pytest_pyq/test_pytest_pyq.py
pytest_pyq/test_pytest_pyq_module.py
pytest_pyq/test_pytest_pyq_session_a.py
pytest_pyq/test_pytest_pyq_session_b.py
pytest_pyq-1.2.0.dist-info/METADATA
pytest_pyq-1.2.0.dist-info/WHEEL
pytest_pyq-1.2.0.dist-info/entry_points.txt
pytest_pyq-1.2.0.dist-info/top_level.txt
pytest_pyq-1.2.0.dist-info/zip-safe
pytest_pyq-1.2.0.dist-info/RECORD
