Metadata-Version: 2.1
Name: pytest-pyq
Version: 1.2.0
Summary: Pytest fixture "q" for pyq
Home-page: http://pyq.enlnt.com
Author: Enlightenment Research, LLC
Author-email: pyq@enlnt.com
License: BSD
Platform: UNKNOWN
Classifier: Development Status :: 5 - Production/Stable
Classifier: Environment :: Console
Classifier: Intended Audience :: Developers
Classifier: License :: OSI Approved :: BSD License
Classifier: Programming Language :: Python
Classifier: Topic :: Software Development :: Quality Assurance
Classifier: Topic :: Software Development :: Testing
